bgm_tv_wiki/__init__.py
bgm_tv_wiki/py.typed
bgm_tv_wiki-0.0.33.dist-info/licenses/LICENSE
bgm_tv_wiki-0.0.33.dist-info/WHEEL
bgm_tv_wiki-0.0.33.dist-info/METADATA
bgm_tv_wiki-0.0.33.dist-info/RECORD
