Metadata-Version: 2.4
Name: bgm-tv-wiki
Version: 0.0.33
Summary: bgm.tv wiki syntax parser
Author-email: trim21 <trim21me@gmail.com>
Requires-Python: >=3.10.0
Classifier: Development Status :: 4 - Beta
Classifier: License :: OSI Approved :: MIT License
Classifier: Programming Language :: Python :: 3 :: Only
License-File: LICENSE
Requires-Dist: pytest==8.4.2 ; extra == "dev"
Requires-Dist: pytest-github-actions-annotate-failures==0.3.0 ; extra == "dev"
Requires-Dist: coverage==7.10.7 ; extra == "dev"
Requires-Dist: mypy==1.18.2 ; extra == "dev" and ( python_version >= "3.9")
Requires-Dist: pyyaml>=6,<7 ; extra == "dev"
Requires-Dist: types-PyYAML ; extra == "dev"
Provides-Extra: dev
